setup.py
cftool/__init__.py
cftool/__main__.py
cftool/config.json
cftool/download.py
cftool/editor.py
cftool/notify.py
cftool/seed.py
cftool/submit.py
cftool/template.cpp
cftool/template.py
cftool/tester.py
cftool/tool.py
cftool/watch.py
cftool/imgs/compilation.png
cftool/imgs/fail.png
cftool/imgs/friend_compilation.png
cftool/imgs/friend_fail.png
cftool/imgs/friend_hack.png
cftool/imgs/friend_ok.png
cftool/imgs/friend_tle.png
cftool/imgs/friend_wa.png
cftool/imgs/hack.png
cftool/imgs/logo.png
cftool/imgs/ok.png
cftool/imgs/tle.png
cftool/imgs/wa.png
codeforces_tool.egg-info/PKG-INFO
codeforces_tool.egg-info/SOURCES.txt
codeforces_tool.egg-info/dependency_links.txt
codeforces_tool.egg-info/entry_points.txt
codeforces_tool.egg-info/requires.txt
codeforces_tool.egg-info/top_level.txt