Metadata-Version: 1.0
Name: codeforces-tool
Version: 0.6.2
Summary: Codeforces tool python command line application.
Home-page: UNKNOWN
Author: Roberto Sales
Author-email: iseme.beto@gmail.com
License: UNKNOWN
Platform: UNKNOWN
